discord_linker_pythonAPI/dlxedd_client.py
discord_linker_pythonAPI/errors.py
discord_linker_pythonAPI/wordpress_client.py
docs/doc_creator/build.py
docs/doc_creator/source/conf.py
discord_linker_pythonapi-0.2.9.dist-info/METADATA
discord_linker_pythonapi-0.2.9.dist-info/WHEEL
discord_linker_pythonapi-0.2.9.dist-info/licenses/LICENSE
discord_linker_pythonapi-0.2.9.dist-info/RECORD
